Module_7+1/MIPS-32.v
module MIPS32_Processor(clk1, clk2);

    input clk1, clk2;   //TWO-PHASE Clock

    reg [31:0] PC, IF_ID_IR, IF_ID_NPC, MEM_WB_IR;
    reg [31:0] ID_EX_IR, ID_EX_NPC, ID_EX_A, ID_EX_B, ID_EX_Imm;
    reg[2:0] ID_EX_type, EX_MEM_type, MEM_WB_type;
    reg[31:0] EX_MEM_IR, EX_MEM_ALUOut, EX_MEM_B, MEM_WB_ALUOut, MEM_WB_LMD;
    reg EX_MEM_cond;

    reg[31:0] Reg[0:31];    //Register Bank 32x32
    reg[31:0] Mem [0:1023]; //1024x32 memory

    parameter ADD = 6'b000000, SUB = 6'b000001, AND = 6'b000010, OR = 6'b000011, SLT = 6'b000100, MUL = 6'b000101, HLT = 6'b111111, LW = 6'b001000, SW = 6'b001001, ADDI = 6'b001010, SUBI = 6'b001011, SLTI = 6'b001100, BNEQZ = 6'b001101, BEQZ = 6'b001110;

    parameter RR_ALU = 3'b000, RM_ALU = 3'b001, LOAD = 3'b010, STORE = 3'b011, BRANCH = 3'b100, HALT = 3'b101;

    reg HALTED;
        // Set after HLT instruction is compeleted (in WB stage)

    reg TAKEN_BRANCH;
        // Required to disable instructions after branch

    always @(posedge clk1)      //IF STAGE
        if(HALTED == 0)
            begin
                if( (EX_MEM_IR[31:26] == BEQZ && EX_MEM_cond == 1) || (EX_MEM_IR[31:26] == BNEQZ && EX_MEM_cond == 1) ) //here condition flag represent actually cond = (A==0)  
                    begin
                        IF_ID_IR <= #2 Mem[EX_MEM_ALUOut];
                        TAKEN_BRANCH <= #2 1'b1;
                        IF_ID_NPC <= #2 EX_MEM_ALUOut; // +1 ? 
                        PC <= #2 EX_MEM_ALUOut;
                    end
                else
                    begin
                      IF_ID_IR <= #2 Mem[PC];
                      IF_ID_NPC <= #2 PC + 1;
                      PC <= #2 PC + 1;
                    end
            end

    always @(posedge clk2)      //ID STAGE
        if(HALTED == 0)
            begin
                if(IF_ID_IR[25:21] == 5'b00000) ID_EX_A <= 0;
                else ID_EX_A <= #2 Reg[IF_ID_IR[25:21]];

                if(IF_ID_IR[20:16] == 5'b00000) ID_EX_B <= 0;
                else ID_EX_B <= #2 Reg[IF_ID_IR[20:16]];

                ID_EX_NPC <= #2 IF_ID_NPC;
                ID_EX_IR <= #2 IF_ID_IR;
                ID_EX_Imm <= #2 { {16{IF_ID_IR[15]}}, IF_ID_IR[15:0] };
            
            case (IF_ID_IR[31:26])
                ADD, SUB, AND, OR, SLT, MUL: ID_EX_type <= #2 RR_ALU;
                ADDI, SUBI, SLTI: ID_EX_type <= #2 RM_ALU;
                LW: ID_EX_type <= #2 LOAD;
                SW: ID_EX_type <= #2 STORE;
                BNEQZ, BEQZ: ID_EX_type <= #2 BRANCH;
                HLT: ID_EX_type <= #2 HALT;
                default: ID_EX_type <= #2 HALT; //INVALID OPCODE CASE we stop the machine
            endcase
        end

        always @(posedge clk1)      //EX STAGE
            if(HALTED == 0)
                begin
                    EX_MEM_type <= #2 ID_EX_type;
                    EX_MEM_IR <= #2 ID_EX_IR;
                    TAKEN_BRANCH <= #2 0;

                    case (ID_EX_type) 

                        RR_ALU:
                            begin 
                                case (ID_EX_IR[31:26]) // "opcode" 
                                    ADD: EX_MEM_ALUOut     <= #2 ID_EX_A + ID_EX_B; 
                                    SUB: EX_MEM_ALUOut     <= #2 ID_EX_A - ID_EX_B; 
                                    AND: EX_MEM_ALUOut     <= #2 ID_EX_A & ID_EX_B; 
                                    OR:  EX_MEM_ALUOut     <= #2 ID_EX_A | ID_EX_B; 
                                    SLT: EX_MEM_ALUOut     <= #2 ID_EX_A < ID_EX_B; 
                                    MUL: EX_MEM_ALUOut     <= #2 ID_EX_A * ID_EX_B; 
                                    default: EX_MEM_ALUOut <= #2 32'hxxxxxxxx; 
                                endcase
                            end

                        RM_ALU:
                            begin 
                                case (ID_EX_IR[31:26]) // "opcode" 
                                    ADDI: EX_MEM_ALUOut    <= #2 ID_EX_A + ID_EX_Imm; 
                                    SUBI: EX_MEM_ALUOut    <= #2 ID_EX_A - ID_EX_Imm; 
                                    SLTI: EX_MEM_ALUOut    <= #2 ID_EX_A < ID_EX_Imm; 
                                    default: EX_MEM_ALUOut <= #2 32'hxxxxxxxx; 
                                endcase
                            end

                        LOAD, STORE: 
                            begin 
                               EX_MEM_ALUOut <= #2 ID_EX_A + ID_EX_Imm; 
                               EX_MEM_B      <= #2 ID_EX_B; 
                             end

                        BRANCH: 
                            begin 
                                EX_MEM_ALUOut <= #2 ID_EX_NPC + ID_EX_Imm; 
                                case(ID_EX_IR[31:26])
                                    BEQZ: EX_MEM_cond <= #2 (ID_EX_A == 0);
                                    BNEQZ: EX_MEM_cond <= #2 (ID_EX_A != 0);
                                endcase
                            end 
                    endcase
                end
        
        always @(posedge clk2)      //MEM STAGE
            if(HALTED == 0)
                begin
                    MEM_WB_type <= EX_MEM_type;
                    MEM_WB_IR <= #2 EX_MEM_IR;

                    case(EX_MEM_type)
                        RR_ALU, RM_ALU: MEM_WB_ALUOut <= #2 EX_MEM_ALUOut;
                        LOAD:   MEM_WB_LMD  <= #2 Mem[EX_MEM_ALUOut];
                        STORE: if(TAKEN_BRANCH == 0) 
                                    begin//disable write
                                        Mem[EX_MEM_ALUOut] <= #2 EX_MEM_B;
                                    end
                    endcase
                end
        
        always @(posedge clk1)      //WB STAGE
            begin
                if(TAKEN_BRANCH == 0)       //DISABLE WRITE IF BRANCH TAKEN
                case(MEM_WB_type)

                    RR_ALU: Reg[MEM_WB_IR[15:11]] <= #2 MEM_WB_ALUOut; // "rd"

                    RM_ALU: Reg[MEM_WB_IR[20:16]] <= #2 MEM_WB_ALUOut; // "rt"

                    LOAD:   Reg[MEM_WB_IR[20:16]] <= #2 MEM_WB_LMD; // "rt"

                    HALT:   HALTED <= #2 1'b1;
                
                endcase
            end
endmodule

Module_7+1/MIPS-32-test1.v
//ADDING THREE NUMBERS 10, 20, 30 stored in processor registers
module test_mips32;
    reg clk1, clk2;
    integer k;

    MIPS32_Processor MIPS(clk1, clk2);

    initial
        begin  
            clk1 = 0; clk2 =0;      //Generating a two phase clock
            repeat(20)
                begin
                    #5 clk1 = 1; #5 clk1 = 0;
                    #5 clk2 = 1; #5 clk2 = 0;
                end
        end


    initial
        begin 
            for (k = 0 ; k < 31 ; k++)
                MIPS.Reg[k] = k;
            
                MIPS.Mem[0] = 32'h2801000a;  // ADDI   R1, R0,10
                MIPS.Mem[1] = 32'h28020014;  // ADDI   R2, R0,20
                MIPS.Mem[2] = 32'h28030019;  // ADDI   R3, R0,25
                MIPS.Mem[3] = 32'h0ce77800;  // OR     R7, R7, R7  -- dummy instr.
                MIPS.Mem[4] = 32'h0ce77800;  // OR     R7, R7, R7  -- dummy instr.
                MIPS.Mem[5] = 32'h00222000;  // ADD    R4, R1, R2
                MIPS.Mem[6] = 32'h0ce77800;  // OR     R7, R7, R7  -- dummy instr.
                MIPS.Mem[7] = 32'h00832800;  // ADD    R5, R4, R3
                MIPS.Mem[8] = 32'hfc000000;  // HLT

                MIPS.HALTED = 0;
                MIPS.PC = 0;
                MIPS.TAKEN_BRANCH = 0;

                #280
                for(k=0; k<6; k++)
                    $display("R%1d = %2d", k, MIPS.Reg[k]);
        end
                
    initial 
        begin
            $dumpfile("mip-vals.vcd");
            $dumpvars(0, test_mips32);
            #300 $finish;
        end
endmodule

Module_7+1/mip-vals.vcd
$date
	Thu Mar 27 01:35:37 2025
$end
$version
	Icarus Verilog
$end
$timescale
	1s
$end
$scope module test_mips32 $end
$var reg 1 ! clk1 $end
$var reg 1 " clk2 $end
$var integer 32 # k [31:0] $end
$scope module MIPS $end
$var wire 1 ! clk1 $end
$var wire 1 " clk2 $end
$var parameter 6 $ ADD $end
$var parameter 6 % ADDI $end
$var parameter 6 & AND $end
$var parameter 6 ' BEQZ $end
$var parameter 6 ( BNEQZ $end
$var parameter 3 ) BRANCH $end
$var parameter 3 * HALT $end
$var parameter 6 + HLT $end
$var parameter 3 , LOAD $end
$var parameter 6 - LW $end
$var parameter 6 . MUL $end
$var parameter 6 / OR $end
$var parameter 3 0 RM_ALU $end
$var parameter 3 1 RR_ALU $end
$var parameter 6 2 SLT $end
$var parameter 6 3 SLTI $end
$var parameter 3 4 STORE $end
$var parameter 6 5 SUB $end
$var parameter 6 6 SUBI $end
$var parameter 6 7 SW $end
$var reg 32 8 EX_MEM_ALUOut [31:0] $end
$var reg 32 9 EX_MEM_B [31:0] $end
$var reg 32 : EX_MEM_IR [31:0] $end
$var reg 1 ; EX_MEM_cond $end
$var reg 3 < EX_MEM_type [2:0] $end
$var reg 1 = HALTED $end
$var reg 32 > ID_EX_A [31:0] $end
$var reg 32 ? ID_EX_B [31:0] $end
$var reg 32 @ ID_EX_IR [31:0] $end
$var reg 32 A ID_EX_Imm [31:0] $end
$var reg 32 B ID_EX_NPC [31:0] $end
$var reg 3 C ID_EX_type [2:0] $end
$var reg 32 D IF_ID_IR [31:0] $end
$var reg 32 E IF_ID_NPC [31:0] $end
$var reg 32 F MEM_WB_ALUOut [31:0] $end
$var reg 32 G MEM_WB_IR [31:0] $end
$var reg 32 H MEM_WB_LMD [31:0] $end
$var reg 3 I MEM_WB_type [2:0] $end
$var reg 32 J PC [31:0] $end
$var reg 1 K TAKEN_BRANCH $end
$upscope $end
$upscope $end
$enddefinitions $end
$comment Show the parameter values. $end
$dumpall
b1001 7
b1011 6
b1 5
b11 4
b1100 3
b100 2
b0 1
b1 0
b11 /
b101 .
b1000 -
b10 ,
b111111 +
b101 *
b100 )
b1101 (
b1110 '
b10 &
b1010 %
b0 $
$end
#0
$dumpvars
0K
b0 J
bx I
bx H
bx G
bx F
bx E
bx D
bx C
bx B
bx A
bx @
bx ?
bx >
0=
bx <
x;
bx :
bx 9
bx 8
b100000 #
0"
0!
$end
#5
1!
#7
b1 J
b1 E
b101000000010100000000011001000 D
#10
0!
#15
b0 >
1"
#17
b1 C
b11001000 A
b101000000010100000000011001000 @
b1 B
b1010 ?
#20
0"
#25
1!
#27
b11001000 8
b101000000010100000000011001000 :
b1 <
b10 J
b10 E
b101000000000100000000000000001 D
#30
0!
#35
b1 I
1"
#37
b11001000 F
b101000000010100000000011001000 G
b1 A
b101000000000100000000000000001 @
b10 B
b10 ?
#40
0"
#45
1!
#47
b11 J
b11 E
b100001010000110000000000000000 D
b1 8
b101000000000100000000000000001 :
#50
0!
#55
1"
#57
b10 C
b0 A
b100001010000110000000000000000 @
b11 B
b11 ?
b11001000 >
b1 F
b101000000000100000000000000001 G
#60
0"
#65
1!
#67
b11 9
b11001000 8
b100001010000110000000000000000 :
b10 <
b100 J
b100 E
b1110100101001010000000000000 D
#70
0!
#75
b10 I
1"
#77
b111 H
b100001010000110000000000000000 G
b0 C
b11111111111111111010000000000000 A
b1110100101001010000000000000 @
b100 B
b10100 ?
b10100 >
#80
0"
#85
1!
#87
b101 J
b101 E
b10100010000110001000000000000 D
b10100 8
b1110100101001010000000000000 :
b0 <
#90
0!
#95
b0 I
1"
#97
b1000000000000 A
b10100010000110001000000000000 @
b101 B
b111 ?
b1 >
b10100 F
b1110100101001010000000000000 G
#100
0"
#105
1!
#107
b111 8
b10100010000110001000000000000 :
b110 J
b110 E
b101100011000110000000000000001 D
#110
0!
#115
1"
#117
b111 F
b10100010000110001000000000000 G
b1 C
b1 A
b101100011000110000000000000001 @
b110 B
b111 >
#120
0"
#125
1!
#127
b111 J
b111 E
b1110100101001010000000000000 D
b110 8
b101100011000110000000000000001 :
b1 <
#130
0!
#135
b1 I
1"
#137
b0 C
b11111111111111111010000000000000 A
b1110100101001010000000000000 @
b111 B
b10100 ?
b10100 >
b110 F
b101100011000110000000000000001 G
#140
0"
#145
1!
#147
b10100 8
b1110100101001010000000000000 :
b0 <
b1000 J
b1000 E
b110100011000001111111111111100 D
#150
0!
#155
b0 I
b0 ?
1"
#157
b10100 F
b1110100101001010000000000000 G
b100 C
b11111111111111111111111111111100 A
b110100011000001111111111111100 @
b1000 B
b110 >
#160
0"
#165
1!
#167
b1001 J
b1001 E
b100101010000101111111111111110 D
1;
b100 8
b110100011000001111111111111100 :
b100 <
#170
0!
#175
b100 I
1"
#177
b11 C
b11111111111111111111111111111110 A
b100101010000101111111111111110 @
b1001 B
b111 ?
b11001000 >
b110100011000001111111111111100 G
#180
0"
#185
1!
#187
b111 9
b11000110 8
b100101010000101111111111111110 :
b11 <
b100 J
b100 E
0K
b10100010000110001000000000000 D
#190
0!
#195
b11 I
1"
#197
b100101010000101111111111111110 G
b0 C
b1000000000000 A
b10100010000110001000000000000 @
b100 B
b110 ?
b111 >
#200
0"
#205
1!
#207
b101 J
b101 E
b101010 8
b10100010000110001000000000000 :
b0 <
#210
0!
#215
b0 I
1"
#217
b101 B
b101010 F
b10100010000110001000000000000 G
#220
0"
#225
1!
#227
b110 J
b110 E
b101100011000110000000000000001 D
#230
0!
#235
1"
#237
b1 C
b1 A
b101100011000110000000000000001 @
b110 B
b110 >
#240
0"
#245
1!
#247
b111 J
b111 E
b1110100101001010000000000000 D
b101 8
b101100011000110000000000000001 :
b1 <
#250
0!
#255
b1 I
1"
#257
b0 C
b11111111111111111010000000000000 A
b1110100101001010000000000000 @
b111 B
b10100 ?
b10100 >
b101 F
b101100011000110000000000000001 G
#260
0"
#265
1!
#267
b10100 8
b1110100101001010000000000000 :
b0 <
b1000 J
b1000 E
b110100011000001111111111111100 D
#270
0!
#275
b0 I
b0 ?
1"
#277
b10100 F
b1110100101001010000000000000 G
b100 C
b11111111111111111111111111111100 A
b110100011000001111111111111100 @
b1000 B
b101 >
#280
0"
#285
1!
#287
b1001 J
b1001 E
b100101010000101111111111111110 D
b100 8
b110100011000001111111111111100 :
b100 <
#290
0!
#295
b100 I
1"
#297
b11 C
b11111111111111111111111111111110 A
b100101010000101111111111111110 @
b1001 B
b101010 ?
b11001000 >
b110100011000001111111111111100 G
#300
0"
#305
1!
#307
b101010 9
b11000110 8
b100101010000101111111111111110 :
b11 <
b100 J
b100 E
0K
b10100010000110001000000000000 D
#310
0!
#315
b11 I
1"
#317
b100101010000101111111111111110 G
b0 C
b1000000000000 A
b10100010000110001000000000000 @
b100 B
b101 ?
b101010 >
#320
0"
#325
1!
#327
b101 J
b101 E
b11010010 8
b10100010000110001000000000000 :
b0 <
#330
0!
#335
b0 I
1"
#337
b101 B
b11010010 F
b10100010000110001000000000000 G
#340
0"
#345
1!
#347
b110 J
b110 E
b101100011000110000000000000001 D
#350
0!
#355
1"
#357
b1 C
b1 A
b101100011000110000000000000001 @
b110 B
b101 >
#360
0"
#365
1!
#367
b111 J
b111 E
b1110100101001010000000000000 D
b100 8
b101100011000110000000000000001 :
b1 <
#370
0!
#375
b1 I
1"
#377
b0 C
b11111111111111111010000000000000 A
b1110100101001010000000000000 @
b111 B
b10100 ?
b10100 >
b100 F
b101100011000110000000000000001 G
#380
0"
#385
1!
#387
b10100 8
b1110100101001010000000000000 :
b0 <
b1000 J
b1000 E
b110100011000001111111111111100 D
#390
0!
#395
b0 I
b0 ?
1"
#397
b10100 F
b1110100101001010000000000000 G
b100 C
b11111111111111111111111111111100 A
b110100011000001111111111111100 @
b1000 B
b100 >
#400
0"
#405
1!
#407
b1001 J
b1001 E
b100101010000101111111111111110 D
b100 8
b110100011000001111111111111100 :
b100 <
#410
0!
#415
b100 I
1"
#417
b11 C
b11111111111111111111111111111110 A
b100101010000101111111111111110 @
b1001 B
b11010010 ?
b11001000 >
b110100011000001111111111111100 G
#420
0"
#425
1!
#427
b11010010 9
b11000110 8
b100101010000101111111111111110 :
b11 <
b100 J
b100 E
0K
b10100010000110001000000000000 D
#430
0!
#435
b11 I
1"
#437
b100101010000101111111111111110 G
b0 C
b1000000000000 A
b10100010000110001000000000000 @
b100 B
b100 ?
b11010010 >
#440
0"
#445
1!
#447
b101 J
b101 E
b1101001000 8
b10100010000110001000000000000 :
b0 <
#450
0!
#455
b0 I
1"
#457
b101 B
b1101001000 F
b10100010000110001000000000000 G
#460
0"
#465
1!
#467
b110 J
b110 E
b101100011000110000000000000001 D
#470
0!
#475
1"
#477
b1 C
b1 A
b101100011000110000000000000001 @
b110 B
b100 >
#480
0"
#485
1!
#487
b111 J
b111 E
b1110100101001010000000000000 D
b11 8
b101100011000110000000000000001 :
b1 <
#490
0!
#495
b1 I
1"
#497
b0 C
b11111111111111111010000000000000 A
b1110100101001010000000000000 @
b111 B
b10100 ?
b10100 >
b11 F
b101100011000110000000000000001 G
#500
0"
#505
1!
#507
b10100 8
b1110100101001010000000000000 :
b0 <
b1000 J
b1000 E
b110100011000001111111111111100 D
#510
0!
#515
b0 I
b0 ?
1"
#517
b10100 F
b1110100101001010000000000000 G
b100 C
b11111111111111111111111111111100 A
b110100011000001111111111111100 @
b1000 B
b11 >
#520
0"
#525
1!
#527
b1001 J
b1001 E
b100101010000101111111111111110 D
b100 8
b110100011000001111111111111100 :
b100 <
#530
0!
#535
b100 I
1"
#537
b11 C
b11111111111111111111111111111110 A
b100101010000101111111111111110 @
b1001 B
b1101001000 ?
b11001000 >
b110100011000001111111111111100 G
#540
0"
#545
1!
#547
b1101001000 9
b11000110 8
b100101010000101111111111111110 :
b11 <
b100 J
b100 E
0K
b10100010000110001000000000000 D
#550
0!
#555
b11 I
1"
#557
b100101010000101111111111111110 G
b0 C
b1000000000000 A
b10100010000110001000000000000 @
b100 B
b11 ?
b1101001000 >
#560
0"
#565
1!
#567
b101 J
b101 E
b100111011000 8
b10100010000110001000000000000 :
b0 <
#570
0!
#575
b0 I
1"
#577
b101 B
b100111011000 F
b10100010000110001000000000000 G
#580
0"
#585
1!
#587
b110 J
b110 E
b101100011000110000000000000001 D
#590
0!
#595
1"
#597
b1 C
b1 A
b101100011000110000000000000001 @
b110 B
b11 >
#600
0"
#605
1!
#607
b111 J
b111 E
b1110100101001010000000000000 D
b10 8
b101100011000110000000000000001 :
b1 <
#610
0!
#615
b1 I
1"
#617
b0 C
b11111111111111111010000000000000 A
b1110100101001010000000000000 @
b111 B
b10100 ?
b10100 >
b10 F
b101100011000110000000000000001 G
#620
0"
#625
1!
#627
b10100 8
b1110100101001010000000000000 :
b0 <
b1000 J
b1000 E
b110100011000001111111111111100 D
#630
0!
#635
b0 I
b0 ?
1"
#637
b10100 F
b1110100101001010000000000000 G
b100 C
b11111111111111111111111111111100 A
b110100011000001111111111111100 @
b1000 B
b10 >
#640
0"
#645
1!
#647
b1001 J
b1001 E
b100101010000101111111111111110 D
b100 8
b110100011000001111111111111100 :
b100 <
#650
0!
#655
b100 I
1"
#657
b11 C
b11111111111111111111111111111110 A
b100101010000101111111111111110 @
b1001 B
b100111011000 ?
b11001000 >
b110100011000001111111111111100 G
#660
0"
#665
1!
#667
b100111011000 9
b11000110 8
b100101010000101111111111111110 :
b11 <
b100 J
b100 E
0K
b10100010000110001000000000000 D
#670
0!
#675
b11 I
1"
#677
b100101010000101111111111111110 G
b0 C
b1000000000000 A
b10100010000110001000000000000 @
b100 B
b10 ?
b100111011000 >
#680
0"
#685
1!
#687
b101 J
b101 E
b1001110110000 8
b10100010000110001000000000000 :
b0 <
#690
0!
#695
b0 I
1"
#697
b101 B
b1001110110000 F
b10100010000110001000000000000 G
#700
0"
#705
1!
#707
b110 J
b110 E
b101100011000110000000000000001 D
#710
0!
#715
1"
#717
b1 C
b1 A
b101100011000110000000000000001 @
b110 B
b10 >
#720
0"
#725
1!
#727
b111 J
b111 E
b1110100101001010000000000000 D
b1 8
b101100011000110000000000000001 :
b1 <
#730
0!
#735
b1 I
1"
#737
b0 C
b11111111111111111010000000000000 A
b1110100101001010000000000000 @
b111 B
b10100 ?
b10100 >
b1 F
b101100011000110000000000000001 G
#740
0"
#745
1!
#747
b10100 8
b1110100101001010000000000000 :
b0 <
b1000 J
b1000 E
b110100011000001111111111111100 D
#750
0!
#755
b0 I
b0 ?
1"
#757
b10100 F
b1110100101001010000000000000 G
b100 C
b11111111111111111111111111111100 A
b110100011000001111111111111100 @
b1000 B
b1 >
#760
0"
#765
1!
#767
b1001 J
b1001 E
b100101010000101111111111111110 D
b100 8
b110100011000001111111111111100 :
b100 <
#770
0!
#775
b100 I
1"
#777
b11 C
b11111111111111111111111111111110 A
b100101010000101111111111111110 @
b1001 B
b1001110110000 ?
b11001000 >
b110100011000001111111111111100 G
#780
0"
#785
1!
#787
b1001110110000 9
b11000110 8
b100101010000101111111111111110 :
b11 <
b100 J
b100 E
0K
b10100010000110001000000000000 D
#790
0!
#795
b11 I
1"
#797
b100101010000101111111111111110 G
b0 C
b1000000000000 A
b10100010000110001000000000000 @
b100 B
b1 ?
b1001110110000 >
#800
0"
#805
1!
#807
b101 J
b101 E
b1001110110000 8
b10100010000110001000000000000 :
b0 <
#810
0!
#815
b0 I
1"
#817
b101 B
b1001110110000 F
b10100010000110001000000000000 G
#820
0"
#825
1!
#827
b110 J
b110 E
b101100011000110000000000000001 D
#830
0!
#835
1"
#837
b1 C
b1 A
b101100011000110000000000000001 @
b110 B
b1 >
#840
0"
#845
1!
#847
b111 J
b111 E
b1110100101001010000000000000 D
b0 8
b101100011000110000000000000001 :
b1 <
#850
0!
#855
b1 I
1"
#857
b0 C
b11111111111111111010000000000000 A
b1110100101001010000000000000 @
b111 B
b10100 ?
b10100 >
b0 F
b101100011000110000000000000001 G
#860
0"
#865
1!
#867
b10100 8
b1110100101001010000000000000 :
b0 <
b1000 J
b1000 E
b110100011000001111111111111100 D
#870
0!
#875
b0 I
b0 ?
1"
#877
b10100 F
b1110100101001010000000000000 G
b100 C
b11111111111111111111111111111100 A
b110100011000001111111111111100 @
b1000 B
b0 >
#880
0"
#885
1!
#887
b1001 J
b1001 E
b100101010000101111111111111110 D
0;
b100 8
b110100011000001111111111111100 :
b100 <
#890
0!
#895
b100 I
1"
#897
b11 C
b11111111111111111111111111111110 A
b100101010000101111111111111110 @
b1001 B
b1001110110000 ?
b11001000 >
b110100011000001111111111111100 G
#900
0"
#905
1!
#907
b11000110 8
b100101010000101111111111111110 :
b11 <
b1010 J
b1010 E
b11111100000000000000000000000000 D
#910
0!
#915
b11 I
b0 ?
b0 >
1"
#917
b100101010000101111111111111110 G
b101 C
b0 A
b11111100000000000000000000000000 @
b1010 B
#920
0"
#925
1!
#927
b1011 J
b1011 E
bx D
b11111100000000000000000000000000 :
b101 <
#930
0!
#935
b101 I
1"
#937
bx A
bx @
b1011 B
bx ?
bx >
b11111100000000000000000000000000 G
#940
0"
#945
1!
#947
1=
bx :
b1100 J
b1100 E
