Module_6+1/6_Pipeline_Simple_Exmaple.v
module pipeline_simple_exmaple (A, B, C, D, F, clk);
    parameter N = 10;

    input [N-1:0] A, B, C, D;
    input clk;
    output [N-1:0] F;

    reg [N-1:0] L12_X1, L12_X2, L12_D, L23_X3, L23_D, L34_F;
    
    assign F = L34_F;

    always @(posedge clk)
        begin
            //Stage 1
            #4 L12_X1 <= A + B;
            #4 L12_X2 <= C - D;
            L12_D <= D;
        end
    
    always @(posedge clk)
        begin
            //Stage 2
            #4 L23_X3 <= L12_X1 + L12_X2;
            L23_D <= L12_D;
        end

    always @(posedge clk)
        begin
            //Stage 3
            #6 L34_F = L23_X3 * L23_D;
        end
endmodule

Module_6+1/6_Pipeline_Simple_Exmaple-test.v
module tester;
    parameter N = 10;
    reg [N-1:0] A, B, C, D;
    wire [N-1:0] F;
    reg clk;

    pipeline_simple_exmaple DUT(A, B, C, D, F, clk);

    initial
        begin
            clk = 0;
            forever 
                #10 clk = ~clk;
        end
    
    initial
        begin
            #5  A = 10; B = 12; C = 6; D = 3;    // F = 75  (4Bh)
            #20 A = 10; B = 10; C = 5; D = 3;    // F = 66  (42h)
            #20 A = 20; B = 11; C = 1; D = 4;    // F = 112 (70h)
            #20 A = 15; B = 10; C = 8; D = 2;    // F = 62  (3Eh)
            #20 A = 8;  B = 15; C = 5; D = 0;    // F = 0   (00h)
            #20 A = 10; B = 20; C = 5; D = 3;    // F = 66  (42h)
            #20 A = 10; B = 10; C = 30; D = 1;   // F = 49  (31h)
            #20 A = 30; B = 1; C = 2; D = 4;     // F = 116 (74h)
        end

    initial
        begin
            $dumpfile ("pipel1.vcd");
            $dumpvars (0, tester);
            $monitor ("Time: %d, F = %d", $time, F);   //(time usually monitor ni krta)
            #300 $finish;
        end
endmodule

//Notice after 3 cycles 1st output appears as it should but after that with each cycle a new output comes, this is the benefit of pipeline modelling

Module_6+1/pipel1.vcd
$date
	Mon Mar 24 13:37:50 2025
$end
$version
	Icarus Verilog
$end
$timescale
	1s
$end
$scope module tester $end
$var wire 10 ! F [9:0] $end
$var parameter 32 " N $end
$var reg 10 # A [9:0] $end
$var reg 10 $ B [9:0] $end
$var reg 10 % C [9:0] $end
$var reg 10 & D [9:0] $end
$var reg 1 ' clk $end
$scope module DUT $end
$var wire 10 ( A [9:0] $end
$var wire 10 ) B [9:0] $end
$var wire 10 * C [9:0] $end
$var wire 10 + D [9:0] $end
$var wire 10 , F [9:0] $end
$var wire 1 ' clk $end
$var parameter 32 - N $end
$var reg 10 . L12_D [9:0] $end
$var reg 10 / L12_X1 [9:0] $end
$var reg 10 0 L12_X2 [9:0] $end
$var reg 10 1 L23_D [9:0] $end
$var reg 10 2 L23_X3 [9:0] $end
$var reg 10 3 L34_F [9:0] $end
$upscope $end
$upscope $end
$enddefinitions $end
$comment Show the parameter values. $end
$dumpall
b1010 -
b1010 "
$end
#0
$dumpvars
bx 3
bx 2
bx 1
bx 0
bx /
bx .
bx ,
bx +
bx *
bx )
bx (
0'
bx &
bx %
bx $
bx #
bx !
$end
#5
b11 &
b11 +
b110 %
b110 *
b1100 $
b1100 )
b1010 #
b1010 (
#10
1'
#14
b10110 /
#18
b11 .
b11 0
#20
0'
#25
b101 %
b101 *
b1010 $
b1010 )
#30
1'
#34
b11 1
b11001 2
b10100 /
#36
b1001011 !
b1001011 ,
b1001011 3
#38
b10 0
#40
0'
#45
b100 &
b100 +
b1 %
b1 *
b1011 $
b1011 )
b10100 #
b10100 (
#50
1'
#54
b10110 2
b11111 /
#56
b1000010 !
b1000010 ,
b1000010 3
#58
b100 .
b1111111101 0
#60
0'
#65
b10 &
b10 +
b1000 %
b1000 *
b1010 $
b1010 )
b1111 #
b1111 (
#70
1'
#74
b100 1
b11100 2
b11001 /
#76
b1110000 !
b1110000 ,
b1110000 3
#78
b10 .
b110 0
#80
0'
#85
b0 &
b0 +
b101 %
b101 *
b1111 $
b1111 )
b1000 #
b1000 (
#90
1'
#94
b10 1
b11111 2
b10111 /
#96
b111110 !
b111110 ,
b111110 3
#98
b0 .
b101 0
#100
0'
#105
b11 &
b11 +
b10100 $
b10100 )
b1010 #
b1010 (
#110
1'
#114
b0 1
b11100 2
b11110 /
#116
b0 !
b0 ,
b0 3
#118
b11 .
b10 0
#120
0'
#125
b1 &
b1 +
b11110 %
b11110 *
b1010 $
b1010 )
#130
1'
#134
b11 1
b100000 2
b10100 /
#136
b1100000 !
b1100000 ,
b1100000 3
#138
b1 .
b11101 0
#140
0'
#145
b100 &
b100 +
b10 %
b10 *
b1 $
b1 )
b11110 #
b11110 (
#150
1'
#154
b1 1
b110001 2
b11111 /
#156
b110001 !
b110001 ,
b110001 3
#158
b100 .
b1111111110 0
#160
0'
#170
1'
#174
b100 1
b11101 2
#176
b1110100 !
b1110100 ,
b1110100 3
