Module_6+1/7_Pipeline_Complex_Example.v
module pipeline_complex(Zout, rs1, rs2, rd, func, addr, clk1, clk2);
    input [3:0] rs1, rs2, rd, func;
    input [7:0] addr;
    input clk1, clk2;
    output [15:0] Zout; 

    reg [15:0] L12_A, L12_B, L23_Z, L34_Z;
    reg [3:0] L12_rd, L12_func, L23_rd;
    reg [7:0] L12_addr, L23_addr, L34_addr;

    reg [15:0] regbank[0:15];
    reg [15:0] memory[0:255];

    assign Zout = L34_Z;

    always @(posedge clk1)
        begin
            L12_A <= #2 regbank[rs1];
            L12_B <= #2 regbank[rs2];
            L12_rd <= #2 rd;
            L12_addr <= #2 addr;
            L12_func <= #2 func;
        end 

    always @(posedge clk2)
        begin
            case(func)
                0 : L23_Z <= #2 L12_A + L12_B;
                1 : L23_Z <= #2 L12_A - L12_B;
                2 : L23_Z <= #2 L12_A * L12_B;
                3 : L23_Z <= #2 L12_A;
                4 : L23_Z <= #2 L12_B;
                5 : L23_Z <= #2 L12_A & L12_B;
                6 : L23_Z <= #2 L12_A | L12_B;
                7 : L23_Z <= #2 L12_A ^ L12_B;
                8 : L23_Z <= #2 ~L12_A;
                9 : L23_Z <= #2 ~L12_B;
                10 : L23_Z <= #2 L12_A >> 1;
                11 : L23_Z <= #2 L12_A << 1;
                default: #2 L23_Z <= 16'hxxxx;
            endcase
            L23_rd <= #2 L12_rd;
            L23_addr <= #2 L12_addr;
        end 

    always @(posedge clk1)
        begin
            regbank[L23_rd] <= #2 L23_Z;
            L34_addr <= #2 L23_addr;
            L34_Z <= #2 L23_Z;
        end 

    always @(posedge clk2)
        begin
            memory[L34_addr] <= #2 L34_Z;
        end 
        
endmodule

Module_6+1/7_Pipeline_Complex_Example-test.v
module tester;
    reg [3:0] rs1, rs2, rd, func;
    reg [7:0] addr;
    reg clk1, clk2;
    wire [15:0] Zout;
    integer k;

    pipeline_complex DUT(Zout, rs1, rs2, rd, func, addr, clk1, clk2);

    initial 
        begin
            clk1 = 0; clk2 = 0;
        end
    
    // always 
    //     begin
    //         #5 clk1 = ~clk1;
    //         #15 clk1 = ~clk1;
    //     end

    // always 
    //     begin
    //         #15 clk2 = ~clk2;
    //         #5 clk2 = ~clk2;
    //     end

//Or more accurately as:

    always
        begin
            #5 clk1 = 1;
            #5 clk1 = 0;
            #5 clk2 = 1;
            #5 clk2 = 0;
        end

    initial 
        begin
            for(k = 0; k < 16; k = k + 1)
                DUT.regbank[k] = k; //Initializing registers
        end

    initial
        begin
            #4  rs1 = 3;   rs2 = 5;   rd = 1;  func = 0;   addr = 1;  // ADD
            #20  rs1 = 3;   rs2 = 8;   rd = 2;  func = 2;   addr = 2;  // MUL
            #20  rs1 = 10;  rs2 = 0;   rd = 3;  func = 1;   addr = 3;  // SUB
            #20  rs1 = 2;   rs2 = 3;   rd = 4;  func = 11;  addr = 4;  // SLA
            #20  rs1 = 14;  rs2 = 5;   rd = 5;  func = 1;   addr = 5;  // SUB
            #20  rs1 = 15;  rs2 = 13;  rd = 6;  func = 0;   addr = 6;  // ADD
            //NOTE
                //REGBANK ITSELF IS CHANGING SO DONT USE THE ONES IN rd again AS those will be altered
            // #60 for (k=1; k<7; k=k+1)
            //     $display ("Mem[%1d] = %d", k, DUT.memory[k]);
        end

    initial
        begin
            $dumpfile ("pipe2.vcd");
            $dumpvars (0, tester);
            $monitor ("Time: %3d, Zout = %3d", $time, Zout);
            #300 $finish;
        end

endmodule

Module_6+1/pipe2.vcd
$date
	Mon Mar 24 20:20:54 2025
$end
$version
	Icarus Verilog
$end
$timescale
	1s
$end
$scope module tester $end
$var wire 16 ! Zout [15:0] $end
$var reg 8 " addr [7:0] $end
$var reg 1 # clk1 $end
$var reg 1 $ clk2 $end
$var reg 4 % func [3:0] $end
$var reg 4 & rd [3:0] $end
$var reg 4 ' rs1 [3:0] $end
$var reg 4 ( rs2 [3:0] $end
$var integer 32 ) k [31:0] $end
$scope module DUT $end
$var wire 16 * Zout [15:0] $end
$var wire 8 + addr [7:0] $end
$var wire 1 # clk1 $end
$var wire 1 $ clk2 $end
$var wire 4 , func [3:0] $end
$var wire 4 - rd [3:0] $end
$var wire 4 . rs1 [3:0] $end
$var wire 4 / rs2 [3:0] $end
$var reg 16 0 L12_A [15:0] $end
$var reg 16 1 L12_B [15:0] $end
$var reg 8 2 L12_addr [7:0] $end
$var reg 4 3 L12_func [3:0] $end
$var reg 4 4 L12_rd [3:0] $end
$var reg 16 5 L23_Z [15:0] $end
$var reg 8 6 L23_addr [7:0] $end
$var reg 4 7 L23_rd [3:0] $end
$var reg 16 8 L34_Z [15:0] $end
$var reg 8 9 L34_addr [7:0] $end
$upscope $end
$upscope $end
$enddefinitions $end
$comment Show the parameter values. $end
$dumpall
$end
#0
$dumpvars
bx 9
bx 8
bx 7
bx 6
bx 5
bx 4
bx 3
bx 2
bx 1
bx 0
bx /
bx .
bx -
bx ,
bx +
bx *
b10000 )
bx (
bx '
bx &
bx %
0$
0#
bx "
bx !
$end
#4
b1 "
b1 +
b0 %
b0 ,
b111 &
b111 -
b101 (
b101 /
b11 '
b11 .
#5
1#
#7
b0 3
b1 2
b111 4
b101 1
b11 0
#10
0#
#15
1$
#17
b1 6
b111 7
b1000 5
#20
0$
#24
b10 "
b10 +
b10 %
b10 ,
b11 &
b11 -
b1000 (
b1000 /
#25
1#
#27
b1000 !
b1000 *
b1000 8
b1 9
b10 3
b10 2
b11 4
b1000 1
#30
0#
#35
1$
#37
b10 6
b11 7
b11000 5
#40
0$
#44
b11 "
b11 +
b1 %
b1 ,
b1001 &
b1001 -
b0 (
b0 /
b1010 '
b1010 .
#45
1#
#47
b1 3
b11 2
b1001 4
b0 1
b1010 0
b11000 !
b11000 *
b11000 8
b10 9
#50
0#
#55
1$
#57
b11 6
b1001 7
b1010 5
#60
0$
#64
b100 "
b100 +
b1011 %
b1011 ,
b1010 &
b1010 -
b11 (
b11 /
b10 '
b10 .
#65
1#
#67
b1010 !
b1010 *
b1010 8
b11 9
b1011 3
b100 2
b1010 4
b11000 1
b10 0
#70
0#
#75
1$
#77
b100 6
b1010 7
b100 5
#80
0$
#84
b101 "
b101 +
b1 %
b1 ,
b1011 &
b1011 -
b101 (
b101 /
b1110 '
b1110 .
#85
1#
#87
b1 3
b101 2
b1011 4
b101 1
b1110 0
b100 !
b100 *
b100 8
b100 9
#90
0#
#95
1$
#97
b101 6
b1011 7
b1001 5
#100
0$
#104
b110 "
b110 +
b0 %
b0 ,
b1100 &
b1100 -
b1101 (
b1101 /
b1111 '
b1111 .
#105
1#
#107
b1001 !
b1001 *
b1001 8
b101 9
b0 3
b110 2
b1100 4
b1101 1
b1111 0
#110
0#
#115
1$
#117
b110 6
b1100 7
b11100 5
#120
0$
#125
1#
#127
b11100 !
b11100 *
b11100 8
b110 9
