Module_5+1/1_multiply_progressive_add.v
module PIPO1(X, Bus, ldA, clk);
    input [15:0] Bus;
    input ldA, clk;
    output reg [15:0] X;

    always @(posedge clk)
        if(ldA) X <= Bus;

endmodule

module PIPO2(Y, Z, ldP, clrP, clk);
    input [15:0] Z;
    input ldP, clrP, clk;
    output reg [15:0] Y;

        always @(posedge clk)
            begin
                if(clrP) Y <= 16'b0;
                else if(ldP) Y <= Z;
            end
endmodule

module Counter(Bout, Bus, ldB, decB, clk);
    input [15:0] Bus;
    input ldB, decB, clk;
    output reg [15:0] Bout;
    
    always @(posedge clk)
        begin
            if(ldB) Bout <= Bus;
            else if(decB) Bout <= Bout - 1;
        end
endmodule

module Adder (Z, X, Y);
    input [15:0] X, Y;
    output reg [15:0] Z;

    always @(*)
        Z = X + Y;
endmodule

module EQZ(eqz, Bout);
    input [15:0] Bout;
    output reg eqz;
    always @(*)
            eqz = (Bout == 0);
endmodule

module datapath_mul(eqz, ldA, ldB, ldP, clrP, decB, data_in, clk);
    input ldA, ldB, ldP, clrP, decB, clk; //(these are like the commands)
    input [15:0] data_in;
    output eqz;
    wire [15:0] X, Y, Z, Bout, Bus;

    assign Bus = data_in;

    PIPO1 A(X, Bus, ldA, clk);
    PIPO2 P(Y, Z, ldP, clrP, clk);
    Counter B(Bout, Bus, ldB, decB, clk);
    Adder Add(Z, X, Y);
    EQZ Comp(eqz, Bout);
endmodule

//STANDARD WAY
// module controlpath_mul(eqz, ldA, ldB, ldP, clrP, decB, start, done, clk);
//     input eqz, start, clk;
//     output reg ldA, ldB, ldP, clrP, decB, done;

//     reg [1:0] i;
//     initial i = 2'b00;
//     reg [2:0] state;
//     parameter S0 = 3'b000, S1 = 3'b001, S2 = 3'b010, S3 = 3'b011, S4 = 3'b100;
//     always @(posedge clk)
//         begin
//             case(state)
//                 S0: state <= S1;
//                 S1: state <= S2;
//                 S2: state <= S3;
//                 S3: begin 
//                         #2 if(!eqz)  begin  state <= S3; i = 2'b01; end //little delay for synchronization to get eqz value
//                         else begin state <= S4; i = 2'b10; end  // i just as a checker bcz i got slow 18/03/2025
//                     end
//                 S4: state <= S4;
//                 default: state <= S0;
//             endcase
//         end

//     always @(state)    //I did mistake putting it posedge clk
//         begin
//             case(state)
//                 S0: #1 begin ldA = 0; ldB = 0; ldP = 0; decB = 0; clrP = 0; done = 0; end
//                 S1: #1 begin ldA = 1; end
//                 S2: #1 begin ldA = 0; ldB = 1; clrP = 1; end
//                 S3: #1 begin ldB = 0; decB = 1; ldP = 1; clrP = 0; end
//                 S4: #1 begin decB = 0; ldP = 0; done = 1; end
//                 default: #1 begin ldA = 0; ldB = 0; ldP = 0; decB = 0; clrP = 0;end 
//             endcase
//         end
// endmodule

//ALTERNATIVE WAY
module controlpath_mul(eqz, ldA, ldB, ldP, clrP, decB, start, done, clk);
    input eqz, start, clk;
    output reg ldA, ldB, ldP, clrP, decB, done;

    reg [2:0] state, next_state;
    parameter S0 = 3'b000, S1 = 3'b001, S2 = 3'b010, S3 = 3'b011, S4 = 3'b100;

    always @(posedge clk)
        if(eqz == 1) state <= S4; //kyuki posedge ke saath hi eqz value de ra tha i didnt had choice
        else state <= next_state;
    
    initial #5 state = S0;
    always @(state)    //I did mistake putting it posedge clk
        begin
            case(state)
                S0: #1 begin ldA = 0; ldB = 0; ldP = 0; decB = 0; clrP = 0; done = 0; next_state = S1; end
                S1: #1 begin ldA = 1; next_state = S2; end
                S2: #1 begin ldA = 0; ldB = 1; clrP = 1; next_state = S3; end
                S3: #1 begin  ldB = 0; decB = 1; ldP = 1; clrP = 0; next_state = S3; end
                S4: #1 begin decB = 0; ldP = 0; done = 1; next_state = S4; end
                default: #1 begin ldA = 0; ldB = 0; ldP = 0; decB = 0; clrP = 0; next_state = S0; end 
            endcase
        end
endmodule

Module_5+1/1_multiply_progressive_add-test.v
module tester;
    reg [15:0] data_in;
    reg clk, start;
    
    datapath_mul DP(eqz, ldA, ldB, ldP, clrP, decB, data_in, clk);
    controlpath_mul CP(eqz, ldA, ldB, ldP, clrP, decB, start, done, clk);

    initial 
        begin 
            clk = 1'b0;
            #3 start = 1'b1;
            #500 $finish;
        end
    
    always 
        #5 clk = ~clk;

    initial 
        begin
            $dumpfile("mul_values.vcd");
            $dumpvars(0, tester);
            $monitor($time, " Value = %d, Done = %1b, A = %2d, B = %2d, State = %d,", DP.Y, CP.done, DP.X, DP.Bout, CP.state, CP.eqz);
        end
    
    initial 
        begin
            #17 data_in = 100;
            #10 data_in = 17;
        end
endmodule

//THE GTK VALUES ARE IN HEXADECIMAL those x,y,z ones

Module_5+1/mul_values.vcd
$date
	Thu Mar 20 12:41:53 2025
$end
$version
	Icarus Verilog
$end
$timescale
	1s
$end
$scope module tester $end
$var wire 1 ! ldP $end
$var wire 1 " ldB $end
$var wire 1 # ldA $end
$var wire 1 $ eqz $end
$var wire 1 % done $end
$var wire 1 & decB $end
$var wire 1 ' clrP $end
$var reg 1 ( clk $end
$var reg 16 ) data_in [15:0] $end
$var reg 1 * start $end
$scope module CP $end
$var wire 1 ( clk $end
$var wire 1 * start $end
$var wire 1 $ eqz $end
$var parameter 3 + S0 $end
$var parameter 3 , S1 $end
$var parameter 3 - S2 $end
$var parameter 3 . S3 $end
$var parameter 3 / S4 $end
$var reg 1 ' clrP $end
$var reg 1 & decB $end
$var reg 1 % done $end
$var reg 1 # ldA $end
$var reg 1 " ldB $end
$var reg 1 ! ldP $end
$var reg 3 0 next_state [2:0] $end
$var reg 3 1 state [2:0] $end
$upscope $end
$scope module DP $end
$var wire 16 2 Bus [15:0] $end
$var wire 1 ( clk $end
$var wire 1 ' clrP $end
$var wire 16 3 data_in [15:0] $end
$var wire 1 & decB $end
$var wire 1 # ldA $end
$var wire 1 " ldB $end
$var wire 1 ! ldP $end
$var wire 1 $ eqz $end
$var wire 16 4 Z [15:0] $end
$var wire 16 5 Y [15:0] $end
$var wire 16 6 X [15:0] $end
$var wire 16 7 Bout [15:0] $end
$scope module A $end
$var wire 16 8 Bus [15:0] $end
$var wire 1 ( clk $end
$var wire 1 # ldA $end
$var reg 16 9 X [15:0] $end
$upscope $end
$scope module Add $end
$var wire 16 : X [15:0] $end
$var wire 16 ; Y [15:0] $end
$var reg 16 < Z [15:0] $end
$upscope $end
$scope module B $end
$var wire 16 = Bus [15:0] $end
$var wire 1 ( clk $end
$var wire 1 & decB $end
$var wire 1 " ldB $end
$var reg 16 > Bout [15:0] $end
$upscope $end
$scope module Comp $end
$var wire 16 ? Bout [15:0] $end
$var reg 1 $ eqz $end
$upscope $end
$scope module P $end
$var wire 16 @ Z [15:0] $end
$var wire 1 ( clk $end
$var wire 1 ' clrP $end
$var wire 1 ! ldP $end
$var reg 16 A Y [15:0] $end
$upscope $end
$upscope $end
$upscope $end
$enddefinitions $end
$comment Show the parameter values. $end
$dumpall
b100 /
b11 .
b10 -
b1 ,
b0 +
$end
#0
$dumpvars
bx A
bx @
bx ?
bx >
bx =
bx <
bx ;
bx :
bx 9
bx 8
bx 7
bx 6
bx 5
bx 4
bx 3
bx 2
bx 1
bx 0
x*
bx )
0(
x'
x&
x%
x$
x#
x"
x!
$end
#3
1*
#5
1(
bx 1
#6
b1 0
0%
0'
0&
0!
0"
0#
#10
0(
#15
b1 1
1(
#16
b10 0
1#
#17
b1100100 2
b1100100 8
b1100100 =
b1100100 )
b1100100 3
#20
0(
#25
b1100100 6
b1100100 9
b1100100 :
b10 1
1(
#26
b11 0
1'
1"
0#
#27
b10001 2
b10001 8
b10001 =
b10001 )
b10001 3
#30
0(
#35
0$
b1100100 4
b1100100 <
b1100100 @
b11 1
b10001 7
b10001 >
b10001 ?
b0 5
b0 ;
b0 A
1(
#36
0'
1!
1&
0"
#40
0(
#45
b11001000 4
b11001000 <
b11001000 @
b1100100 5
b1100100 ;
b1100100 A
b10000 7
b10000 >
b10000 ?
1(
#50
0(
#55
b100101100 4
b100101100 <
b100101100 @
b1111 7
b1111 >
b1111 ?
b11001000 5
b11001000 ;
b11001000 A
1(
#60
0(
#65
b110010000 4
b110010000 <
b110010000 @
b100101100 5
b100101100 ;
b100101100 A
b1110 7
b1110 >
b1110 ?
1(
#70
0(
#75
b111110100 4
b111110100 <
b111110100 @
b1101 7
b1101 >
b1101 ?
b110010000 5
b110010000 ;
b110010000 A
1(
#80
0(
#85
b1001011000 4
b1001011000 <
b1001011000 @
b111110100 5
b111110100 ;
b111110100 A
b1100 7
b1100 >
b1100 ?
1(
#90
0(
#95
b1010111100 4
b1010111100 <
b1010111100 @
b1011 7
b1011 >
b1011 ?
b1001011000 5
b1001011000 ;
b1001011000 A
1(
#100
0(
#105
b1100100000 4
b1100100000 <
b1100100000 @
b1010111100 5
b1010111100 ;
b1010111100 A
b1010 7
b1010 >
b1010 ?
1(
#110
0(
#115
b1110000100 4
b1110000100 <
b1110000100 @
b1001 7
b1001 >
b1001 ?
b1100100000 5
b1100100000 ;
b1100100000 A
1(
#120
0(
#125
b1111101000 4
b1111101000 <
b1111101000 @
b1110000100 5
b1110000100 ;
b1110000100 A
b1000 7
b1000 >
b1000 ?
1(
#130
0(
#135
b10001001100 4
b10001001100 <
b10001001100 @
b111 7
b111 >
b111 ?
b1111101000 5
b1111101000 ;
b1111101000 A
1(
#140
0(
#145
b10010110000 4
b10010110000 <
b10010110000 @
b10001001100 5
b10001001100 ;
b10001001100 A
b110 7
b110 >
b110 ?
1(
#150
0(
#155
b10100010100 4
b10100010100 <
b10100010100 @
b101 7
b101 >
b101 ?
b10010110000 5
b10010110000 ;
b10010110000 A
1(
#160
0(
#165
b10101111000 4
b10101111000 <
b10101111000 @
b10100010100 5
b10100010100 ;
b10100010100 A
b100 7
b100 >
b100 ?
1(
#170
0(
#175
b10111011100 4
b10111011100 <
b10111011100 @
b11 7
b11 >
b11 ?
b10101111000 5
b10101111000 ;
b10101111000 A
1(
#180
0(
#185
b11001000000 4
b11001000000 <
b11001000000 @
b10111011100 5
b10111011100 ;
b10111011100 A
b10 7
b10 >
b10 ?
1(
#190
0(
#195
b11010100100 4
b11010100100 <
b11010100100 @
b1 7
b1 >
b1 ?
b11001000000 5
b11001000000 ;
b11001000000 A
1(
#200
0(
#205
b11100001000 4
b11100001000 <
b11100001000 @
1$
b11010100100 5
b11010100100 ;
b11010100100 A
b0 7
b0 >
b0 ?
1(
#210
0(
#215
0$
b11101101100 4
b11101101100 <
b11101101100 @
b100 1
b1111111111111111 7
b1111111111111111 >
b1111111111111111 ?
b11100001000 5
b11100001000 ;
b11100001000 A
1(
#216
b100 0
1%
0!
0&
